test/__init__.py
test/test_ynab.py
test/support/__init__.py
test/support/dummy_client.py
test/support/mock.py
test/support/fixtures/__init__.py
test/support/fixtures/accounts.py
test/support/fixtures/budgets.py
test/support/fixtures/categories.py
test/support/fixtures/payees.py
test/support/fixtures/transactions.py
test/test_api/__init__.py
test/test_api/test_accounts.py
test/test_api/test_budgets.py
test/test_api/test_categories.py
test/test_api/test_payees.py
test/test_api/test_transactions.py
test/test_utils/__init__.py
test/test_utils/clients/__init__.py
test/test_utils/clients/test_cached_client.py
test/test_utils/clients/test_default_client.py
ynab_sdk/__init__.py
ynab_sdk/ynab.py
ynab_sdk/api/__init__.py
ynab_sdk/api/accounts.py
ynab_sdk/api/budgets.py
ynab_sdk/api/categories.py
ynab_sdk/api/payees.py
ynab_sdk/api/transactions.py
ynab_sdk/api/models/__init__.py
ynab_sdk/api/models/requests/__init__.py
ynab_sdk/api/models/requests/accounts.py
ynab_sdk/api/models/requests/transaction.py
ynab_sdk/api/models/responses/__init__.py
ynab_sdk/api/models/responses/account.py
ynab_sdk/api/models/responses/accounts.py
ynab_sdk/api/models/responses/budget_detail.py
ynab_sdk/api/models/responses/budget_settings.py
ynab_sdk/api/models/responses/budget_summary.py
ynab_sdk/api/models/responses/categories.py
ynab_sdk/api/models/responses/category.py
ynab_sdk/api/models/responses/payee.py
ynab_sdk/api/models/responses/payees.py
ynab_sdk/api/models/responses/transactions.py
ynab_sdk/utils/__init__.py
ynab_sdk/utils/exception.py
ynab_sdk/utils/parsers.py
ynab_sdk/utils/responses.py
ynab_sdk/utils/clients/__init__.py
ynab_sdk/utils/clients/base_client.py
ynab_sdk/utils/clients/cached_client.py
ynab_sdk/utils/clients/default_client.py
ynab_sdk/utils/configurations/__init__.py
ynab_sdk/utils/configurations/cached.py
ynab_sdk/utils/configurations/default.py
ynab_sdk-0.5.0.dist-info/LICENSE
ynab_sdk-0.5.0.dist-info/METADATA
ynab_sdk-0.5.0.dist-info/WHEEL
ynab_sdk-0.5.0.dist-info/top_level.txt
ynab_sdk-0.5.0.dist-info/RECORD
