Metadata-Version: 2.1
Name: ynab-sdk
Version: 0.5.0
Summary: YNAB API Endpoints
Home-page: https://github.com/andreroggeri/ynab-sdk-python
Author-email: a.roggeri.c@gmail.com
Keywords: YNAB,YNAB API Endpoints,
License-File: LICENSE
Requires-Dist: requests
Requires-Dist: python-dateutil
Requires-Dist: redis
